diagnostic/__init__.py
diagnostic/_base.py
diagnostic/_check_docs.py
diagnostic/_concrete.py
diagnostic/_parsers.py
diagnostic/check-docs.py
diagnostic/py.typed
diagnostic-3.0.0.dist-info/licenses/LICENSE
diagnostic-3.0.0.dist-info/WHEEL
diagnostic-3.0.0.dist-info/METADATA
diagnostic-3.0.0.dist-info/RECORD
